socks5/__init__.py
socks5/client/__init__.py
socks5/client/core.py
socks5/server/__init__.py
socks5/server/__main__.py
socks5/server/_socks5.py
socks5/server/authentications.py
socks5/server/exceptions.py
socks5/server/server.py
socks5/server/sessions.py
socks5/types.py
socks5/utils.py
socks5/values.py
asyncio_socks5-0.2.11.dist-info/LICENSE
asyncio_socks5-0.2.11.dist-info/WHEEL
asyncio_socks5-0.2.11.dist-info/METADATA
asyncio_socks5-0.2.11.dist-info/RECORD
